datasnap/__init__.py
datasnap/core.py
datasnap-0.1.0.dist-info/LICENSE.txt
datasnap-0.1.0.dist-info/METADATA
datasnap-0.1.0.dist-info/WHEEL
datasnap-0.1.0.dist-info/top_level.txt
datasnap-0.1.0.dist-info/RECORD
