Metadata-Version: 2.1
Name: datasnap
Version: 0.1.0
Summary: A tool to generate quick data insights and column recommendations for dataframes
Home-page: https://github.com/ShelbyTO/datasnap
Author: Nicolas Prieur
Author-email: pu-zle@live.fr
License: MIT
Classifier: Programming Language :: Python :: 3
Classifier: License :: OSI Approved :: MIT License
Classifier: Operating System :: OS Independent
Requires-Python: >=3.6
License-File: LICENSE.txt
Requires-Dist: pandas
